pytemppack/__init__.py
pytemppack/py_pack.py
pytemppack/utils.py
pytemppack-0.0.0.dist-info/LICENSE
pytemppack-0.0.0.dist-info/WHEEL
pytemppack-0.0.0.dist-info/METADATA
pytemppack-0.0.0.dist-info/RECORD
