Metadata-Version: 2.1
Name: pytemppack
Version: 0.0.0
Summary: A python package template with poetry
Home-page: https://www.andresalgaba.com/
License: MIT
Keywords: python,package,template,poetry
Author: Andres Algaba
Author-email: andres.algaba@vub.be
Maintainer: Andres Algaba
Maintainer-email: andres.algaba@vub.be
Requires-Python: >=3.8,<3.10
Classifier: License :: OSI Approved :: MIT License
Classifier: Programming Language :: Python :: 3
Classifier: Programming Language :: Python :: 3.8
Classifier: Programming Language :: Python :: 3.9
Requires-Dist: numpy (>=1.22.3)
Requires-Dist: pandas (>=1.4.2)
Project-URL: Repository, https://github.com/AndresAlgaba/pytemppack
